easyscrape_ebaysuggest/__init__.py
easyscrape_ebaysuggest/querysuggestions.py
easyscrape_ebaysuggest-0.1.2.dist-info/LICENSE
easyscrape_ebaysuggest-0.1.2.dist-info/METADATA
easyscrape_ebaysuggest-0.1.2.dist-info/WHEEL
easyscrape_ebaysuggest-0.1.2.dist-info/top_level.txt
easyscrape_ebaysuggest-0.1.2.dist-info/RECORD
